rayvision_c4d/__init__.py
rayvision_c4d/analyze_c4d.py
rayvision_c4d/constants.py
rayvision_c4d/get_preferences.py
rayvision_c4d/utils.py
rayvision_c4d/tests/__init__.py
rayvision_c4d/tests/conftest.py
rayvision_c4d/tests/test_analyse.py
rayvision_c4d/tests/test_utils.py
rayvision_c4d/tool/RBAnalyzer.pyp
rayvision_c4d/tool/python26/RBAnalyzer.pyd
rayvision_c4d/tool/python27/RBAnalyzer.pyd
rayvision_c4d/tool/python27x/RBAnalyzer.pyd
rayvision_c4d/tool/python310/RBAnalyzer.pyd
rayvision_c4d/tool/python37/RBAnalyzer.pyd
rayvision_c4d/tool/python39/RBAnalyzer.pyd
rayvision_c4d-1.1.1.dist-info/METADATA
rayvision_c4d-1.1.1.dist-info/WHEEL
rayvision_c4d-1.1.1.dist-info/top_level.txt
rayvision_c4d-1.1.1.dist-info/RECORD
